pennsieve/__init__.py
pennsieve/direct/__init__.py
pennsieve/direct/client.py
pennsieve/direct/config.py
pennsieve/direct/provider.py
pennsieve/manifest.py
pennsieve/pennsieve.py
pennsieve/protos/__init__.py
pennsieve/protos/agent.proto
pennsieve/protos/agent_pb2.py
pennsieve/protos/agent_pb2_grpc.py
pennsieve/session.py
pennsieve/timeSeries.py
pennsieve/userProfile.py
pennsieve-7.0.1.dist-info/LICENSE
pennsieve-7.0.1.dist-info/METADATA
pennsieve-7.0.1.dist-info/WHEEL
pennsieve-7.0.1.dist-info/RECORD
