Metadata-Version: 2.3
Name: pennsieve
Version: 7.0.1
Summary: Pennsieve Python Client
License: Apache-2.0
Keywords: data science,datasets
Author: Pennsieve Team
Author-email: support@pennsieve.net
Requires-Python: >=3.9,<3.13
Classifier: Development Status :: 4 - Beta
Classifier: Intended Audience :: Developers
Classifier: Intended Audience :: Information Technology
Classifier: Intended Audience :: Science/Research
Classifier: License :: OSI Approved :: Apache Software License
Classifier: Programming Language :: Python :: 3
Classifier: Programming Language :: Python :: 3.9
Classifier: Programming Language :: Python :: 3.10
Classifier: Programming Language :: Python :: 3.11
Classifier: Programming Language :: Python :: 3.12
Classifier: Topic :: Scientific/Engineering
Classifier: Topic :: Scientific/Engineering :: Bio-Informatics
Classifier: Topic :: Scientific/Engineering :: Information Analysis
Classifier: Topic :: Software Development
Classifier: Topic :: Software Development :: Libraries
Classifier: Topic :: Software Development :: Libraries :: Python Modules
Provides-Extra: dev
Requires-Dist: boto3 (>=1.26,<2.0)
Requires-Dist: grpcio (>=1.51,<2.0)
Requires-Dist: grpcio_tools (>=1.51,<2.0)
Requires-Dist: numpy (==1.26.0)
Requires-Dist: pandas (>=2.2.3,<3.0.0)
Requires-Dist: protobuf (>=4.21,<5.0)
Requires-Dist: pyjwt (>=2.6,<3.0)
Requires-Dist: requests (>=2.28,<3.0)
Requires-Dist: tqdm (>=4.64,<5.0)
Project-URL: changelog, https://github.com/pennsieve/pennsieve-agent-python/CHANGELOG.md
Project-URL: documentation, https://docs.pennsieve.io/docs/uploading-files-programmatically
Project-URL: homepage, https://app.pennsieve.io
Project-URL: repository, https://github.com/pennsieve/pennsieve-agent-python
